my_socket_library/__init__.py
my_socket_library/cli.py
my_socket_library/client.py
my_socket_library/server.py
my_socket_library-0.1.0.dist-info/LICENSE
my_socket_library-0.1.0.dist-info/METADATA
my_socket_library-0.1.0.dist-info/WHEEL
my_socket_library-0.1.0.dist-info/entry_points.txt
my_socket_library-0.1.0.dist-info/top_level.txt
my_socket_library-0.1.0.dist-info/RECORD
