Metadata-Version: 2.1
Name: my_socket_library
Version: 0.1.0
Summary: Библиотека для клиент-серверного взаимодействия через сокеты
Home-page: 
Author: Anonymous
Author-email: anonymous@example.com
Classifier: Programming Language :: Python :: 3
Classifier: License :: OSI Approved :: MIT License
Classifier: Operating System :: OS Independent
Requires-Python: >=3.6
License-File: LICENSE
